[
  {
    "Mood": "Stressed",
    "Location": "dundalk",
    "Timestamp": "2024-10-15T23:55:17.0710227+01:00",
    "Recommendations": [
      "Fairways Hotel Dundalk - Dublin Road, Haggardstown, Dundalk",
      "Imperial Hotel - 95 Park Street, Dundalk",
      "Fairlawns Bed & Breakfast - Dublin Road, Dundalk",
      "Glen Gat Guesthouse - The Crescent, Dundalk",
      "Heritage B&B - Ireland",
      "Ballymascanlon Hotel & Golf Resort - Carlingford Road (R173, Dundalk",
      "The Gateway Hotel • Dundalk - Inner Relief Road, Dundalk",
      "Rosemount B&B - Dublin Road, Dundalk",
      "Krakow B & B - 190 Árd Easmuinn, Dundalk",
      "Keernaun House B&B - Dublin Road, Cocklehill",
      "Mullaharlin Lodge - Mullaharlin Road, Dundalk Road, Dundalk"
    ]
  },
  {
    "Mood": "Stressed",
    "Location": "dundalk",
    "Timestamp": "2024-10-15T23:59:22.7897008+01:00",
    "Recommendations": [
      "Fairways Hotel Dundalk - Dublin Road, Haggardstown, Dundalk",
      "Imperial Hotel - 95 Park Street, Dundalk",
      "Fairlawns Bed & Breakfast - Dublin Road, Dundalk",
      "Glen Gat Guesthouse - The Crescent, Dundalk",
      "Heritage B&B - Ireland",
      "Ballymascanlon Hotel & Golf Resort - Carlingford Road (R173, Dundalk",
      "The Gateway Hotel • Dundalk - Inner Relief Road, Dundalk",
      "Rosemount B&B - Dublin Road, Dundalk",
      "Krakow B & B - 190 Árd Easmuinn, Dundalk",
      "Keernaun House B&B - Dublin Road, Cocklehill",
      "Mullaharlin Lodge - Mullaharlin Road, Dundalk Road, Dundalk"
    ]
  },
  {
    "Mood": "Happy",
    "Location": "Dublin",
    "Timestamp": "2024-10-16T00:09:15.1130194+01:00",
    "Recommendations": [
      "The Morgan Hotel - 10-12 Fleet Street, Temple Bar, Dublin",
      "Temple Bar Inn - 40-47 Fleet Street, Temple Bar, Dublin 2",
      "The College Green Hotel Dublin, Autograph Collection - At, College Green, Dublin",
      "The Shelbourne, Autograph Collection - 27 Saint Stephen's Green, Dublin",
      "Hotel Riu Plaza The Gresham Dublin - 23 O'Connell Street Upper, Dublin",
      "Blooms Hotel - 3-6 Anglesea Street, Temple Bar, Dublin 2",
      "Trinity College Dublin - College Green, Dublin 2",
      "Anantara The Marker Dublin - Grand Canal Quay, Docklands, Dublin",
      "The Ferryman - 35 Sir John Rogerson's Quay, Grand Canal Dock, Dublin",
      "Maldron Hotel Smithfield - Smithfield Market, Smithfield, Dublin",
      "The Davenport Hotel - 8-10 Merrion Street Lower, Dublin",
      "Hilton Garden Inn Dublin City Centre - Custom House Quay, North Wall, Dublin 1",
      "Abbey Court Hostel - 29 Bachelors Walk, Dublin",
      "Maple Hotel Dublin - 75 Gardiner Street Lower, Dublin",
      "Abrahams Hostel - 82-83 Gardiner Street Lower, Dublin 1",
      "Maldron Hotel Parnell Square - Parnell Square West, Rotunda, Dublin 1",
      "The Trinity City Hotel - Pearse Street, Dublin 2",
      "The Spencer Hotel - Excise Walk, International Financial Services Centre, Dublin 1"
    ]
  },
  {
    "Mood": "Happy",
    "Location": "Dublin",
    "Timestamp": "2024-10-16T00:10:01.1642706+01:00",
    "Recommendations": [
      "The Morgan Hotel - 10-12 Fleet Street, Temple Bar, Dublin",
      "Temple Bar Inn - 40-47 Fleet Street, Temple Bar, Dublin 2",
      "The College Green Hotel Dublin, Autograph Collection - At, College Green, Dublin",
      "The Shelbourne, Autograph Collection - 27 Saint Stephen's Green, Dublin",
      "Hotel Riu Plaza The Gresham Dublin - 23 O'Connell Street Upper, Dublin",
      "Blooms Hotel - 3-6 Anglesea Street, Temple Bar, Dublin 2",
      "Trinity College Dublin - College Green, Dublin 2",
      "Anantara The Marker Dublin - Grand Canal Quay, Docklands, Dublin",
      "The Ferryman - 35 Sir John Rogerson's Quay, Grand Canal Dock, Dublin",
      "Maldron Hotel Smithfield - Smithfield Market, Smithfield, Dublin",
      "The Davenport Hotel - 8-10 Merrion Street Lower, Dublin",
      "Hilton Garden Inn Dublin City Centre - Custom House Quay, North Wall, Dublin 1",
      "Abbey Court Hostel - 29 Bachelors Walk, Dublin",
      "Maple Hotel Dublin - 75 Gardiner Street Lower, Dublin",
      "Abrahams Hostel - 82-83 Gardiner Street Lower, Dublin 1",
      "Maldron Hotel Parnell Square - Parnell Square West, Rotunda, Dublin 1",
      "The Trinity City Hotel - Pearse Street, Dublin 2",
      "The Spencer Hotel - Excise Walk, International Financial Services Centre, Dublin 1"
    ]
  },
  {
    "Mood": "Stressed",
    "Location": "Dublin",
    "Timestamp": "2024-10-16T00:12:51.9662786+01:00",
    "Recommendations": [
      "The Morgan Hotel - 10-12 Fleet Street, Temple Bar, Dublin",
      "Temple Bar Inn - 40-47 Fleet Street, Temple Bar, Dublin 2",
      "The College Green Hotel Dublin, Autograph Collection - At, College Green, Dublin",
      "The Shelbourne, Autograph Collection - 27 Saint Stephen's Green, Dublin",
      "Hotel Riu Plaza The Gresham Dublin - 23 O'Connell Street Upper, Dublin",
      "Anantara The Marker Dublin - Grand Canal Quay, Docklands, Dublin",
      "Blooms Hotel - 3-6 Anglesea Street, Temple Bar, Dublin 2",
      "The Ferryman - 35 Sir John Rogerson's Quay, Grand Canal Dock, Dublin",
      "Bonnington Dublin - 4 Star Hotel - 9 Swords Road, Whitehall, Dublin 9",
      "Maldron Hotel Smithfield - Smithfield Market, Smithfield, Dublin",
      "The Davenport Hotel - 8-10 Merrion Street Lower, Dublin",
      "Harcourt Hotel - 60 Harcourt Street, Dublin 2",
      "Hilton Garden Inn Dublin City Centre - Custom House Quay, North Wall, Dublin 1",
      "Abbey Court Hostel - 29 Bachelors Walk, Dublin",
      "Maple Hotel Dublin - 75 Gardiner Street Lower, Dublin",
      "Abrahams Hostel - 82-83 Gardiner Street Lower, Dublin 1",
      "Maldron Hotel Parnell Square - Parnell Square West, Rotunda, Dublin 1"
    ]
  },
  {
    "Mood": "Happy",
    "Location": "Dublin",
    "Timestamp": "2024-10-16T00:15:01.4114492+01:00",
    "Recommendations": [
      "The Morgan Hotel - 10-12 Fleet Street, Temple Bar, Dublin",
      "Temple Bar Inn - 40-47 Fleet Street, Temple Bar, Dublin 2",
      "The College Green Hotel Dublin, Autograph Collection - At, College Green, Dublin",
      "The Shelbourne, Autograph Collection - 27 Saint Stephen's Green, Dublin",
      "Hotel Riu Plaza The Gresham Dublin - 23 O'Connell Street Upper, Dublin",
      "Anantara The Marker Dublin - Grand Canal Quay, Docklands, Dublin",
      "Blooms Hotel - 3-6 Anglesea Street, Temple Bar, Dublin 2",
      "Trinity College Dublin - College Green, Dublin 2",
      "The Ferryman - 35 Sir John Rogerson's Quay, Grand Canal Dock, Dublin",
      "Bonnington Dublin - 4 Star Hotel - 9 Swords Road, Whitehall, Dublin 9",
      "Maldron Hotel Smithfield - Smithfield Market, Smithfield, Dublin",
      "The Davenport Hotel - 8-10 Merrion Street Lower, Dublin",
      "Harcourt Hotel - 60 Harcourt Street, Dublin 2",
      "Hilton Garden Inn Dublin City Centre - Custom House Quay, North Wall, Dublin 1",
      "Abbey Court Hostel - 29 Bachelors Walk, Dublin",
      "Maple Hotel Dublin - 75 Gardiner Street Lower, Dublin",
      "Abrahams Hostel - 82-83 Gardiner Street Lower, Dublin 1",
      "Maldron Hotel Parnell Square - Parnell Square West, Rotunda, Dublin 1"
    ]
  },
  {
    "Mood": "Happy",
    "Location": "Dublin",
    "Timestamp": "2024-10-16T00:15:04.4537601+01:00",
    "Recommendations": [
      "The Morgan Hotel - 10-12 Fleet Street, Temple Bar, Dublin",
      "Temple Bar Inn - 40-47 Fleet Street, Temple Bar, Dublin 2",
      "The College Green Hotel Dublin, Autograph Collection - At, College Green, Dublin",
      "The Shelbourne, Autograph Collection - 27 Saint Stephen's Green, Dublin",
      "Hotel Riu Plaza The Gresham Dublin - 23 O'Connell Street Upper, Dublin",
      "Anantara The Marker Dublin - Grand Canal Quay, Docklands, Dublin",
      "Blooms Hotel - 3-6 Anglesea Street, Temple Bar, Dublin 2",
      "Trinity College Dublin - College Green, Dublin 2",
      "The Ferryman - 35 Sir John Rogerson's Quay, Grand Canal Dock, Dublin",
      "Bonnington Dublin - 4 Star Hotel - 9 Swords Road, Whitehall, Dublin 9",
      "Maldron Hotel Smithfield - Smithfield Market, Smithfield, Dublin",
      "The Davenport Hotel - 8-10 Merrion Street Lower, Dublin",
      "Harcourt Hotel - 60 Harcourt Street, Dublin 2",
      "Hilton Garden Inn Dublin City Centre - Custom House Quay, North Wall, Dublin 1",
      "Abbey Court Hostel - 29 Bachelors Walk, Dublin",
      "Maple Hotel Dublin - 75 Gardiner Street Lower, Dublin",
      "Abrahams Hostel - 82-83 Gardiner Street Lower, Dublin 1",
      "Maldron Hotel Parnell Square - Parnell Square West, Rotunda, Dublin 1"
    ]
  },
  {
    "Mood": "Happy",
    "Location": "Dublin",
    "Timestamp": "2024-10-16T00:15:06.904104+01:00",
    "Recommendations": [
      "The Morgan Hotel - 10-12 Fleet Street, Temple Bar, Dublin",
      "Temple Bar Inn - 40-47 Fleet Street, Temple Bar, Dublin 2",
      "The College Green Hotel Dublin, Autograph Collection - At, College Green, Dublin",
      "The Shelbourne, Autograph Collection - 27 Saint Stephen's Green, Dublin",
      "Hotel Riu Plaza The Gresham Dublin - 23 O'Connell Street Upper, Dublin",
      "Anantara The Marker Dublin - Grand Canal Quay, Docklands, Dublin",
      "Blooms Hotel - 3-6 Anglesea Street, Temple Bar, Dublin 2",
      "Trinity College Dublin - College Green, Dublin 2",
      "The Ferryman - 35 Sir John Rogerson's Quay, Grand Canal Dock, Dublin",
      "Bonnington Dublin - 4 Star Hotel - 9 Swords Road, Whitehall, Dublin 9",
      "Maldron Hotel Smithfield - Smithfield Market, Smithfield, Dublin",
      "The Davenport Hotel - 8-10 Merrion Street Lower, Dublin",
      "Harcourt Hotel - 60 Harcourt Street, Dublin 2",
      "Hilton Garden Inn Dublin City Centre - Custom House Quay, North Wall, Dublin 1",
      "Abbey Court Hostel - 29 Bachelors Walk, Dublin",
      "Maple Hotel Dublin - 75 Gardiner Street Lower, Dublin",
      "Abrahams Hostel - 82-83 Gardiner Street Lower, Dublin 1",
      "Maldron Hotel Parnell Square - Parnell Square West, Rotunda, Dublin 1"
    ]
  },
  {
    "Mood": "Happy",
    "Location": "Dublin",
    "Timestamp": "2024-10-16T00:16:02.6540505+01:00",
    "Recommendations": [
      "The Morgan Hotel - 10-12 Fleet Street, Temple Bar, Dublin",
      "Temple Bar Inn - 40-47 Fleet Street, Temple Bar, Dublin 2",
      "The College Green Hotel Dublin, Autograph Collection - At, College Green, Dublin",
      "The Shelbourne, Autograph Collection - 27 Saint Stephen's Green, Dublin",
      "Hotel Riu Plaza The Gresham Dublin - 23 O'Connell Street Upper, Dublin",
      "Anantara The Marker Dublin - Grand Canal Quay, Docklands, Dublin",
      "Blooms Hotel - 3-6 Anglesea Street, Temple Bar, Dublin 2",
      "Trinity College Dublin - College Green, Dublin 2",
      "The Ferryman - 35 Sir John Rogerson's Quay, Grand Canal Dock, Dublin",
      "Bonnington Dublin - 4 Star Hotel - 9 Swords Road, Whitehall, Dublin 9",
      "Maldron Hotel Smithfield - Smithfield Market, Smithfield, Dublin",
      "The Davenport Hotel - 8-10 Merrion Street Lower, Dublin",
      "Harcourt Hotel - 60 Harcourt Street, Dublin 2",
      "Hilton Garden Inn Dublin City Centre - Custom House Quay, North Wall, Dublin 1",
      "Abbey Court Hostel - 29 Bachelors Walk, Dublin",
      "Maple Hotel Dublin - 75 Gardiner Street Lower, Dublin",
      "Abrahams Hostel - 82-83 Gardiner Street Lower, Dublin 1",
      "Maldron Hotel Parnell Square - Parnell Square West, Rotunda, Dublin 1"
    ]
  },
  {
    "Mood": "Happy",
    "Location": "Dublin",
    "Timestamp": "2024-10-16T00:16:13.6041063+01:00",
    "Recommendations": [
      "The Morgan Hotel - 10-12 Fleet Street, Temple Bar, Dublin",
      "Temple Bar Inn - 40-47 Fleet Street, Temple Bar, Dublin 2",
      "The College Green Hotel Dublin, Autograph Collection - At, College Green, Dublin",
      "The Shelbourne, Autograph Collection - 27 Saint Stephen's Green, Dublin",
      "Hotel Riu Plaza The Gresham Dublin - 23 O'Connell Street Upper, Dublin",
      "Anantara The Marker Dublin - Grand Canal Quay, Docklands, Dublin",
      "Blooms Hotel - 3-6 Anglesea Street, Temple Bar, Dublin 2",
      "Trinity College Dublin - College Green, Dublin 2",
      "The Ferryman - 35 Sir John Rogerson's Quay, Grand Canal Dock, Dublin",
      "Bonnington Dublin - 4 Star Hotel - 9 Swords Road, Whitehall, Dublin 9",
      "Maldron Hotel Smithfield - Smithfield Market, Smithfield, Dublin",
      "The Davenport Hotel - 8-10 Merrion Street Lower, Dublin",
      "Harcourt Hotel - 60 Harcourt Street, Dublin 2",
      "Hilton Garden Inn Dublin City Centre - Custom House Quay, North Wall, Dublin 1",
      "Abbey Court Hostel - 29 Bachelors Walk, Dublin",
      "Maple Hotel Dublin - 75 Gardiner Street Lower, Dublin",
      "Abrahams Hostel - 82-83 Gardiner Street Lower, Dublin 1",
      "Maldron Hotel Parnell Square - Parnell Square West, Rotunda, Dublin 1"
    ]
  },
  {
    "Mood": "Happy",
    "Location": "Dublin",
    "Timestamp": "2024-10-16T00:22:40.1769893+01:00",
    "Recommendations": [
      "The Morgan Hotel - 10-12 Fleet Street, Temple Bar, Dublin",
      "Temple Bar Inn - 40-47 Fleet Street, Temple Bar, Dublin 2",
      "The College Green Hotel Dublin, Autograph Collection - At, College Green, Dublin",
      "The Shelbourne, Autograph Collection - 27 Saint Stephen's Green, Dublin",
      "Hotel Riu Plaza The Gresham Dublin - 23 O'Connell Street Upper, Dublin",
      "Blooms Hotel - 3-6 Anglesea Street, Temple Bar, Dublin 2",
      "Trinity College Dublin - College Green, Dublin 2",
      "Anantara The Marker Dublin - Grand Canal Quay, Docklands, Dublin",
      "The Ferryman - 35 Sir John Rogerson's Quay, Grand Canal Dock, Dublin",
      "Maldron Hotel Smithfield - Smithfield Market, Smithfield, Dublin",
      "The Davenport Hotel - 8-10 Merrion Street Lower, Dublin",
      "Hilton Garden Inn Dublin City Centre - Custom House Quay, North Wall, Dublin 1",
      "Abbey Court Hostel - 29 Bachelors Walk, Dublin",
      "Maple Hotel Dublin - 75 Gardiner Street Lower, Dublin",
      "Abrahams Hostel - 82-83 Gardiner Street Lower, Dublin 1",
      "Maldron Hotel Parnell Square - Parnell Square West, Rotunda, Dublin 1",
      "The Trinity City Hotel - Pearse Street, Dublin 2",
      "The Spencer Hotel - Excise Walk, International Financial Services Centre, Dublin 1"
    ]
  },
  {
    "Mood": "Sad",
    "Location": "drogheda",
    "Timestamp": "2024-10-16T00:23:01.3321471+01:00",
    "Recommendations": [
      "The Westcourt Hotel - 29 West Street, Drogheda",
      "Boyne Valley Hotel & Country Club - Dublin Road, Drogheda",
      "Newgrange Lodge - Staleen Road, Donore",
      "Orley House - Dublin Road, Drogheda",
      "The Glenside - Dublin Road, Drogheda",
      "The D Hotel - Marsh Road, Lagavooren, Drogheda",
      "Aaron Vale Bed and Breakfast - 85 Ashfield Green, Drogheda",
      "Newtown Blues GFC - Newfoundwell Road, Drogheda",
      "Scholars Townhouse Hotel - Scholars Townhouse Hotel, King Street, Drogheda",
      "WINDSOR LODGE - The, 1, North Road, Drogheda",
      "Drogheda Townhouse - 72 George's Street, Drogheda",
      "Spoon and the Stars Hostel - 13 Dublin Road, Drogheda",
      "Killowen House B&B - Woodgrange, Dublin Rd., Drogheda",
      "Newgrange - Newgrange, Donore",
      "Chez Sé - 7 The Cairns, Beaubec, Dublin Road, Drogheda",
      "Signature Furniture - Drogheda Road, M1 Retail Park",
      "Copperwood drogheda - Donore Road, 2 copperwood, Drogheda",
      "Brú na Bóinne - Drogheda"
    ]
  },
  {
    "Mood": "Happy",
    "Location": "Dublin",
    "Timestamp": "2024-10-16T00:23:34.6374179+01:00",
    "Recommendations": [
      "The Morgan Hotel - 10-12 Fleet Street, Temple Bar, Dublin",
      "Temple Bar Inn - 40-47 Fleet Street, Temple Bar, Dublin 2",
      "The College Green Hotel Dublin, Autograph Collection - At, College Green, Dublin",
      "The Shelbourne, Autograph Collection - 27 Saint Stephen's Green, Dublin",
      "Hotel Riu Plaza The Gresham Dublin - 23 O'Connell Street Upper, Dublin",
      "Blooms Hotel - 3-6 Anglesea Street, Temple Bar, Dublin 2",
      "Trinity College Dublin - College Green, Dublin 2",
      "Anantara The Marker Dublin - Grand Canal Quay, Docklands, Dublin",
      "The Ferryman - 35 Sir John Rogerson's Quay, Grand Canal Dock, Dublin",
      "Maldron Hotel Smithfield - Smithfield Market, Smithfield, Dublin",
      "The Davenport Hotel - 8-10 Merrion Street Lower, Dublin",
      "Hilton Garden Inn Dublin City Centre - Custom House Quay, North Wall, Dublin 1",
      "Abbey Court Hostel - 29 Bachelors Walk, Dublin",
      "Maple Hotel Dublin - 75 Gardiner Street Lower, Dublin",
      "Abrahams Hostel - 82-83 Gardiner Street Lower, Dublin 1",
      "Maldron Hotel Parnell Square - Parnell Square West, Rotunda, Dublin 1",
      "The Trinity City Hotel - Pearse Street, Dublin 2",
      "The Spencer Hotel - Excise Walk, International Financial Services Centre, Dublin 1"
    ]
  },
  {
    "Mood": "Happy",
    "Location": "dafgeag",
    "Timestamp": "2024-10-16T00:24:16.9630341+01:00",
    "Recommendations": [
      "No weather data available."
    ]
  },
  {
    "Mood": "Sad",
    "Location": "kufyctm",
    "Timestamp": "2024-10-16T00:25:10.7499772+01:00",
    "Recommendations": [
      "No weather data available."
    ]
  },
  {
    "Mood": "Happy",
    "Location": "Dublin",
    "Timestamp": "2024-10-16T00:32:26.2415032+01:00",
    "Recommendations": [
      "The Morgan Hotel - 10-12 Fleet Street, Temple Bar, Dublin",
      "Temple Bar Inn - 40-47 Fleet Street, Temple Bar, Dublin 2",
      "The College Green Hotel Dublin, Autograph Collection - At, College Green, Dublin",
      "The Shelbourne, Autograph Collection - 27 Saint Stephen's Green, Dublin",
      "Hotel Riu Plaza The Gresham Dublin - 23 O'Connell Street Upper, Dublin",
      "Anantara The Marker Dublin - Grand Canal Quay, Docklands, Dublin",
      "Blooms Hotel - 3-6 Anglesea Street, Temple Bar, Dublin 2",
      "Trinity College Dublin - College Green, Dublin 2",
      "The Ferryman - 35 Sir John Rogerson's Quay, Grand Canal Dock, Dublin",
      "Bonnington Dublin - 4 Star Hotel - 9 Swords Road, Whitehall, Dublin 9",
      "Maldron Hotel Smithfield - Smithfield Market, Smithfield, Dublin",
      "The Davenport Hotel - 8-10 Merrion Street Lower, Dublin",
      "Harcourt Hotel - 60 Harcourt Street, Dublin 2",
      "Hilton Garden Inn Dublin City Centre - Custom House Quay, North Wall, Dublin 1",
      "Abbey Court Hostel - 29 Bachelors Walk, Dublin",
      "Maple Hotel Dublin - 75 Gardiner Street Lower, Dublin",
      "Abrahams Hostel - 82-83 Gardiner Street Lower, Dublin 1",
      "Maldron Hotel Parnell Square - Parnell Square West, Rotunda, Dublin 1"
    ]
  },
  {
    "Mood": "Happy",
    "Location": "Dublin",
    "Timestamp": "2024-10-16T00:33:27.4959818+01:00",
    "Recommendations": [
      "The Morgan Hotel - 10-12 Fleet Street, Temple Bar, Dublin",
      "Temple Bar Inn - 40-47 Fleet Street, Temple Bar, Dublin 2",
      "The College Green Hotel Dublin, Autograph Collection - At, College Green, Dublin",
      "The Shelbourne, Autograph Collection - 27 Saint Stephen's Green, Dublin",
      "Hotel Riu Plaza The Gresham Dublin - 23 O'Connell Street Upper, Dublin",
      "Anantara The Marker Dublin - Grand Canal Quay, Docklands, Dublin",
      "Blooms Hotel - 3-6 Anglesea Street, Temple Bar, Dublin 2",
      "Trinity College Dublin - College Green, Dublin 2",
      "The Ferryman - 35 Sir John Rogerson's Quay, Grand Canal Dock, Dublin",
      "Bonnington Dublin - 4 Star Hotel - 9 Swords Road, Whitehall, Dublin 9",
      "Maldron Hotel Smithfield - Smithfield Market, Smithfield, Dublin",
      "The Davenport Hotel - 8-10 Merrion Street Lower, Dublin",
      "Harcourt Hotel - 60 Harcourt Street, Dublin 2",
      "Hilton Garden Inn Dublin City Centre - Custom House Quay, North Wall, Dublin 1",
      "Abbey Court Hostel - 29 Bachelors Walk, Dublin",
      "Maple Hotel Dublin - 75 Gardiner Street Lower, Dublin",
      "Abrahams Hostel - 82-83 Gardiner Street Lower, Dublin 1",
      "Maldron Hotel Parnell Square - Parnell Square West, Rotunda, Dublin 1"
    ]
  },
  {
    "Mood": "Happy",
    "Location": "Dublin",
    "Timestamp": "2024-10-16T00:41:38.3161281+01:00",
    "Recommendations": [
      "The Morgan Hotel - 10-12 Fleet Street, Temple Bar, Dublin",
      "Temple Bar Inn - 40-47 Fleet Street, Temple Bar, Dublin 2",
      "The College Green Hotel Dublin, Autograph Collection - At, College Green, Dublin",
      "The Shelbourne, Autograph Collection - 27 Saint Stephen's Green, Dublin",
      "Hotel Riu Plaza The Gresham Dublin - 23 O'Connell Street Upper, Dublin",
      "Anantara The Marker Dublin - Grand Canal Quay, Docklands, Dublin",
      "Blooms Hotel - 3-6 Anglesea Street, Temple Bar, Dublin 2",
      "Trinity College Dublin - College Green, Dublin 2",
      "The Ferryman - 35 Sir John Rogerson's Quay, Grand Canal Dock, Dublin",
      "Bonnington Dublin - 4 Star Hotel - 9 Swords Road, Whitehall, Dublin 9",
      "Maldron Hotel Smithfield - Smithfield Market, Smithfield, Dublin",
      "The Davenport Hotel - 8-10 Merrion Street Lower, Dublin",
      "Harcourt Hotel - 60 Harcourt Street, Dublin 2",
      "Hilton Garden Inn Dublin City Centre - Custom House Quay, North Wall, Dublin 1",
      "Abbey Court Hostel - 29 Bachelors Walk, Dublin",
      "Maple Hotel Dublin - 75 Gardiner Street Lower, Dublin",
      "Abrahams Hostel - 82-83 Gardiner Street Lower, Dublin 1",
      "Maldron Hotel Parnell Square - Parnell Square West, Rotunda, Dublin 1"
    ]
  },
  {
    "Mood": "Happy",
    "Location": "Dublin",
    "Timestamp": "2024-10-16T00:52:10.0035231+01:00",
    "Recommendations": [
      "The Morgan Hotel - 10-12 Fleet Street, Temple Bar, Dublin",
      "Temple Bar Inn - 40-47 Fleet Street, Temple Bar, Dublin 2",
      "The College Green Hotel Dublin, Autograph Collection - At, College Green, Dublin",
      "The Shelbourne, Autograph Collection - 27 Saint Stephen's Green, Dublin",
      "Hotel Riu Plaza The Gresham Dublin - 23 O'Connell Street Upper, Dublin",
      "Anantara The Marker Dublin - Grand Canal Quay, Docklands, Dublin",
      "Blooms Hotel - 3-6 Anglesea Street, Temple Bar, Dublin 2",
      "Trinity College Dublin - College Green, Dublin 2",
      "The Ferryman - 35 Sir John Rogerson's Quay, Grand Canal Dock, Dublin",
      "Bonnington Dublin - 4 Star Hotel - 9 Swords Road, Whitehall, Dublin 9",
      "Maldron Hotel Smithfield - Smithfield Market, Smithfield, Dublin",
      "The Davenport Hotel - 8-10 Merrion Street Lower, Dublin",
      "Harcourt Hotel - 60 Harcourt Street, Dublin 2",
      "Hilton Garden Inn Dublin City Centre - Custom House Quay, North Wall, Dublin 1",
      "Abbey Court Hostel - 29 Bachelors Walk, Dublin",
      "Maple Hotel Dublin - 75 Gardiner Street Lower, Dublin",
      "Abrahams Hostel - 82-83 Gardiner Street Lower, Dublin 1",
      "Maldron Hotel Parnell Square - Parnell Square West, Rotunda, Dublin 1"
    ]
  },
  {
    "Mood": "Stressed",
    "Location": "Dublin",
    "Timestamp": "2024-10-16T00:54:55.1212232+01:00",
    "Recommendations": [
      "The Morgan Hotel - 10-12 Fleet Street, Temple Bar, Dublin",
      "Temple Bar Inn - 40-47 Fleet Street, Temple Bar, Dublin 2",
      "The College Green Hotel Dublin, Autograph Collection - At, College Green, Dublin",
      "The Shelbourne, Autograph Collection - 27 Saint Stephen's Green, Dublin",
      "Hotel Riu Plaza The Gresham Dublin - 23 O'Connell Street Upper, Dublin",
      "Anantara The Marker Dublin - Grand Canal Quay, Docklands, Dublin",
      "Blooms Hotel - 3-6 Anglesea Street, Temple Bar, Dublin 2",
      "The Ferryman - 35 Sir John Rogerson's Quay, Grand Canal Dock, Dublin",
      "Bonnington Dublin - 4 Star Hotel - 9 Swords Road, Whitehall, Dublin 9",
      "Maldron Hotel Smithfield - Smithfield Market, Smithfield, Dublin",
      "The Davenport Hotel - 8-10 Merrion Street Lower, Dublin",
      "Harcourt Hotel - 60 Harcourt Street, Dublin 2",
      "Hilton Garden Inn Dublin City Centre - Custom House Quay, North Wall, Dublin 1",
      "Abbey Court Hostel - 29 Bachelors Walk, Dublin",
      "Maple Hotel Dublin - 75 Gardiner Street Lower, Dublin",
      "Abrahams Hostel - 82-83 Gardiner Street Lower, Dublin 1",
      "Maldron Hotel Parnell Square - Parnell Square West, Rotunda, Dublin 1"
    ]
  },
  {
    "Mood": "Happy",
    "Location": "Dublin",
    "Timestamp": "2024-10-16T00:55:13.5018552+01:00",
    "Recommendations": [
      "The Morgan Hotel - 10-12 Fleet Street, Temple Bar, Dublin",
      "Temple Bar Inn - 40-47 Fleet Street, Temple Bar, Dublin 2",
      "The College Green Hotel Dublin, Autograph Collection - At, College Green, Dublin",
      "The Shelbourne, Autograph Collection - 27 Saint Stephen's Green, Dublin",
      "Hotel Riu Plaza The Gresham Dublin - 23 O'Connell Street Upper, Dublin",
      "Anantara The Marker Dublin - Grand Canal Quay, Docklands, Dublin",
      "Blooms Hotel - 3-6 Anglesea Street, Temple Bar, Dublin 2",
      "Trinity College Dublin - College Green, Dublin 2",
      "The Ferryman - 35 Sir John Rogerson's Quay, Grand Canal Dock, Dublin",
      "Bonnington Dublin - 4 Star Hotel - 9 Swords Road, Whitehall, Dublin 9",
      "Maldron Hotel Smithfield - Smithfield Market, Smithfield, Dublin",
      "The Davenport Hotel - 8-10 Merrion Street Lower, Dublin",
      "Harcourt Hotel - 60 Harcourt Street, Dublin 2",
      "Hilton Garden Inn Dublin City Centre - Custom House Quay, North Wall, Dublin 1",
      "Abbey Court Hostel - 29 Bachelors Walk, Dublin",
      "Maple Hotel Dublin - 75 Gardiner Street Lower, Dublin",
      "Abrahams Hostel - 82-83 Gardiner Street Lower, Dublin 1",
      "Maldron Hotel Parnell Square - Parnell Square West, Rotunda, Dublin 1"
    ]
  },
  {
    "Mood": "Sad",
    "Location": "drogheda",
    "Timestamp": "2024-10-16T00:55:24.0138973+01:00",
    "Recommendations": [
      "The Westcourt Hotel - 29 West Street, Drogheda",
      "Boyne Valley Hotel & Country Club - Dublin Road, Drogheda",
      "Newgrange Lodge - Staleen Road, Donore",
      "Orley House - Dublin Road, Drogheda",
      "The Glenside - Dublin Road, Drogheda",
      "The D Hotel - Marsh Road, Lagavooren, Drogheda",
      "Aaron Vale Bed and Breakfast - 85 Ashfield Green, Drogheda",
      "Newtown Blues GFC - Newfoundwell Road, Drogheda",
      "Scholars Townhouse Hotel - Scholars Townhouse Hotel, King Street, Drogheda",
      "WINDSOR LODGE - The, 1, North Road, Drogheda",
      "Drogheda Townhouse - 72 George's Street, Drogheda",
      "Spoon and the Stars Hostel - 13 Dublin Road, Drogheda",
      "Killowen House B&B - Woodgrange, Dublin Rd., Drogheda",
      "Newgrange - Newgrange, Donore",
      "Chez Sé - 7 The Cairns, Beaubec, Dublin Road, Drogheda",
      "Signature Furniture - Drogheda Road, M1 Retail Park",
      "Copperwood drogheda - Donore Road, 2 copperwood, Drogheda",
      "Brú na Bóinne - Drogheda"
    ]
  },
  {
    "Mood": "Sad",
    "Location": "hxfjxfht",
    "Timestamp": "2024-10-16T01:00:49.9345802+01:00",
    "Recommendations": [
      "No weather data available."
    ]
  },
  {
    "Mood": "Happy",
    "Location": "Dublin",
    "Timestamp": "2024-10-16T01:05:58.5510454+01:00",
    "Recommendations": [
      "The Morgan Hotel - 10-12 Fleet Street, Temple Bar, Dublin",
      "Temple Bar Inn - 40-47 Fleet Street, Temple Bar, Dublin 2",
      "The College Green Hotel Dublin, Autograph Collection - At, College Green, Dublin",
      "The Shelbourne, Autograph Collection - 27 Saint Stephen's Green, Dublin",
      "Hotel Riu Plaza The Gresham Dublin - 23 O'Connell Street Upper, Dublin",
      "Blooms Hotel - 3-6 Anglesea Street, Temple Bar, Dublin 2",
      "Trinity College Dublin - College Green, Dublin 2",
      "Anantara The Marker Dublin - Grand Canal Quay, Docklands, Dublin",
      "The Ferryman - 35 Sir John Rogerson's Quay, Grand Canal Dock, Dublin",
      "Maldron Hotel Smithfield - Smithfield Market, Smithfield, Dublin",
      "The Davenport Hotel - 8-10 Merrion Street Lower, Dublin",
      "Hilton Garden Inn Dublin City Centre - Custom House Quay, North Wall, Dublin 1",
      "Abbey Court Hostel - 29 Bachelors Walk, Dublin",
      "Maple Hotel Dublin - 75 Gardiner Street Lower, Dublin",
      "Abrahams Hostel - 82-83 Gardiner Street Lower, Dublin 1",
      "Maldron Hotel Parnell Square - Parnell Square West, Rotunda, Dublin 1",
      "The Trinity City Hotel - Pearse Street, Dublin 2",
      "The Spencer Hotel - Excise Walk, International Financial Services Centre, Dublin 1"
    ]
  },
  {
    "Mood": "Happy",
    "Location": "Dublin",
    "Timestamp": "2024-10-16T01:06:54.1956274+01:00",
    "Recommendations": [
      "The Morgan Hotel - 10-12 Fleet Street, Temple Bar, Dublin",
      "Temple Bar Inn - 40-47 Fleet Street, Temple Bar, Dublin 2",
      "The College Green Hotel Dublin, Autograph Collection - At, College Green, Dublin",
      "The Shelbourne, Autograph Collection - 27 Saint Stephen's Green, Dublin",
      "Hotel Riu Plaza The Gresham Dublin - 23 O'Connell Street Upper, Dublin",
      "Blooms Hotel - 3-6 Anglesea Street, Temple Bar, Dublin 2",
      "Trinity College Dublin - College Green, Dublin 2",
      "Anantara The Marker Dublin - Grand Canal Quay, Docklands, Dublin",
      "The Ferryman - 35 Sir John Rogerson's Quay, Grand Canal Dock, Dublin",
      "Maldron Hotel Smithfield - Smithfield Market, Smithfield, Dublin",
      "The Davenport Hotel - 8-10 Merrion Street Lower, Dublin",
      "Hilton Garden Inn Dublin City Centre - Custom House Quay, North Wall, Dublin 1",
      "Abbey Court Hostel - 29 Bachelors Walk, Dublin",
      "Maple Hotel Dublin - 75 Gardiner Street Lower, Dublin",
      "Abrahams Hostel - 82-83 Gardiner Street Lower, Dublin 1",
      "Maldron Hotel Parnell Square - Parnell Square West, Rotunda, Dublin 1",
      "The Trinity City Hotel - Pearse Street, Dublin 2",
      "The Spencer Hotel - Excise Walk, International Financial Services Centre, Dublin 1"
    ]
  },
  {
    "Mood": "Happy",
    "Location": "ijo;ijoph",
    "Timestamp": "2024-10-16T01:07:25.116422+01:00",
    "Recommendations": [
      "No weather data available."
    ]
  },
  {
    "Mood": "Happy",
    "Location": "Dublin",
    "Timestamp": "2024-10-16T01:08:34.9412363+01:00",
    "Recommendations": [
      "The Morgan Hotel - 10-12 Fleet Street, Temple Bar, Dublin",
      "Temple Bar Inn - 40-47 Fleet Street, Temple Bar, Dublin 2",
      "The College Green Hotel Dublin, Autograph Collection - At, College Green, Dublin",
      "The Shelbourne, Autograph Collection - 27 Saint Stephen's Green, Dublin",
      "Hotel Riu Plaza The Gresham Dublin - 23 O'Connell Street Upper, Dublin",
      "Blooms Hotel - 3-6 Anglesea Street, Temple Bar, Dublin 2",
      "Trinity College Dublin - College Green, Dublin 2",
      "Anantara The Marker Dublin - Grand Canal Quay, Docklands, Dublin",
      "The Ferryman - 35 Sir John Rogerson's Quay, Grand Canal Dock, Dublin",
      "Maldron Hotel Smithfield - Smithfield Market, Smithfield, Dublin",
      "The Davenport Hotel - 8-10 Merrion Street Lower, Dublin",
      "Hilton Garden Inn Dublin City Centre - Custom House Quay, North Wall, Dublin 1",
      "Abbey Court Hostel - 29 Bachelors Walk, Dublin",
      "Maple Hotel Dublin - 75 Gardiner Street Lower, Dublin",
      "Abrahams Hostel - 82-83 Gardiner Street Lower, Dublin 1",
      "Maldron Hotel Parnell Square - Parnell Square West, Rotunda, Dublin 1",
      "The Trinity City Hotel - Pearse Street, Dublin 2",
      "The Spencer Hotel - Excise Walk, International Financial Services Centre, Dublin 1"
    ]
  },
  {
    "Mood": "Happy",
    "Location": "sDVSD\\C",
    "Timestamp": "2024-10-16T01:08:44.249647+01:00",
    "Recommendations": [
      "No weather and recommendation data available."
    ]
  },
  {
    "Mood": "Happy",
    "Location": "sDVSD\\C",
    "Timestamp": "2024-10-16T01:09:25.5160176+01:00",
    "Recommendations": [
      "No weather and recommendation data available."
    ]
  },
  {
    "Mood": "Happy",
    "Location": "Dublin",
    "Timestamp": "2024-10-16T01:10:09.5302231+01:00",
    "Recommendations": [
      "The Morgan Hotel - 10-12 Fleet Street, Temple Bar, Dublin",
      "Temple Bar Inn - 40-47 Fleet Street, Temple Bar, Dublin 2",
      "The College Green Hotel Dublin, Autograph Collection - At, College Green, Dublin",
      "The Shelbourne, Autograph Collection - 27 Saint Stephen's Green, Dublin",
      "Hotel Riu Plaza The Gresham Dublin - 23 O'Connell Street Upper, Dublin",
      "Blooms Hotel - 3-6 Anglesea Street, Temple Bar, Dublin 2",
      "Trinity College Dublin - College Green, Dublin 2",
      "Anantara The Marker Dublin - Grand Canal Quay, Docklands, Dublin",
      "The Ferryman - 35 Sir John Rogerson's Quay, Grand Canal Dock, Dublin",
      "Maldron Hotel Smithfield - Smithfield Market, Smithfield, Dublin",
      "The Davenport Hotel - 8-10 Merrion Street Lower, Dublin",
      "Hilton Garden Inn Dublin City Centre - Custom House Quay, North Wall, Dublin 1",
      "Abbey Court Hostel - 29 Bachelors Walk, Dublin",
      "Maple Hotel Dublin - 75 Gardiner Street Lower, Dublin",
      "Abrahams Hostel - 82-83 Gardiner Street Lower, Dublin 1",
      "Maldron Hotel Parnell Square - Parnell Square West, Rotunda, Dublin 1",
      "The Trinity City Hotel - Pearse Street, Dublin 2",
      "The Spencer Hotel - Excise Walk, International Financial Services Centre, Dublin 1"
    ]
  },
  {
    "Mood": "Happy",
    "Location": "Dublin",
    "Timestamp": "2024-10-16T01:21:07.1810386+01:00",
    "Recommendations": [
      "The Morgan Hotel - 10-12 Fleet Street, Temple Bar, Dublin",
      "Temple Bar Inn - 40-47 Fleet Street, Temple Bar, Dublin 2",
      "The College Green Hotel Dublin, Autograph Collection - At, College Green, Dublin",
      "The Shelbourne, Autograph Collection - 27 Saint Stephen's Green, Dublin",
      "Hotel Riu Plaza The Gresham Dublin - 23 O'Connell Street Upper, Dublin",
      "Blooms Hotel - 3-6 Anglesea Street, Temple Bar, Dublin 2",
      "Trinity College Dublin - College Green, Dublin 2",
      "Anantara The Marker Dublin - Grand Canal Quay, Docklands, Dublin",
      "The Ferryman - 35 Sir John Rogerson's Quay, Grand Canal Dock, Dublin",
      "Maldron Hotel Smithfield - Smithfield Market, Smithfield, Dublin",
      "The Davenport Hotel - 8-10 Merrion Street Lower, Dublin",
      "Hilton Garden Inn Dublin City Centre - Custom House Quay, North Wall, Dublin 1",
      "Abbey Court Hostel - 29 Bachelors Walk, Dublin",
      "Maple Hotel Dublin - 75 Gardiner Street Lower, Dublin",
      "Abrahams Hostel - 82-83 Gardiner Street Lower, Dublin 1",
      "Maldron Hotel Parnell Square - Parnell Square West, Rotunda, Dublin 1",
      "The Trinity City Hotel - Pearse Street, Dublin 2",
      "The Spencer Hotel - Excise Walk, International Financial Services Centre, Dublin 1"
    ]
  },
  {
    "Mood": "Stressed",
    "Location": "\\cvCXZ",
    "Timestamp": "2024-10-16T01:21:17.0313783+01:00",
    "Recommendations": [
      "No weather and recommendation data available."
    ]
  },
  {
    "Mood": "Happy",
    "Location": "Dublin",
    "Timestamp": "2024-10-16T01:23:15.7382666+01:00",
    "Recommendations": [
      "The Morgan Hotel - 10-12 Fleet Street, Temple Bar, Dublin",
      "Temple Bar Inn - 40-47 Fleet Street, Temple Bar, Dublin 2",
      "The College Green Hotel Dublin, Autograph Collection - At, College Green, Dublin",
      "The Shelbourne, Autograph Collection - 27 Saint Stephen's Green, Dublin",
      "Hotel Riu Plaza The Gresham Dublin - 23 O'Connell Street Upper, Dublin",
      "Blooms Hotel - 3-6 Anglesea Street, Temple Bar, Dublin 2",
      "Trinity College Dublin - College Green, Dublin 2",
      "Anantara The Marker Dublin - Grand Canal Quay, Docklands, Dublin",
      "The Ferryman - 35 Sir John Rogerson's Quay, Grand Canal Dock, Dublin",
      "Maldron Hotel Smithfield - Smithfield Market, Smithfield, Dublin",
      "The Davenport Hotel - 8-10 Merrion Street Lower, Dublin",
      "Hilton Garden Inn Dublin City Centre - Custom House Quay, North Wall, Dublin 1",
      "Abbey Court Hostel - 29 Bachelors Walk, Dublin",
      "Maple Hotel Dublin - 75 Gardiner Street Lower, Dublin",
      "Abrahams Hostel - 82-83 Gardiner Street Lower, Dublin 1",
      "Maldron Hotel Parnell Square - Parnell Square West, Rotunda, Dublin 1",
      "The Trinity City Hotel - Pearse Street, Dublin 2",
      "The Spencer Hotel - Excise Walk, International Financial Services Centre, Dublin 1"
    ]
  },
  {
    "Mood": "Happy",
    "Location": "Dublin",
    "Timestamp": "2024-10-16T01:23:59.9499075+01:00",
    "Recommendations": [
      "The Morgan Hotel - 10-12 Fleet Street, Temple Bar, Dublin",
      "Temple Bar Inn - 40-47 Fleet Street, Temple Bar, Dublin 2",
      "The College Green Hotel Dublin, Autograph Collection - At, College Green, Dublin",
      "The Shelbourne, Autograph Collection - 27 Saint Stephen's Green, Dublin",
      "Hotel Riu Plaza The Gresham Dublin - 23 O'Connell Street Upper, Dublin",
      "Blooms Hotel - 3-6 Anglesea Street, Temple Bar, Dublin 2",
      "Trinity College Dublin - College Green, Dublin 2",
      "Anantara The Marker Dublin - Grand Canal Quay, Docklands, Dublin",
      "The Ferryman - 35 Sir John Rogerson's Quay, Grand Canal Dock, Dublin",
      "Maldron Hotel Smithfield - Smithfield Market, Smithfield, Dublin",
      "The Davenport Hotel - 8-10 Merrion Street Lower, Dublin",
      "Hilton Garden Inn Dublin City Centre - Custom House Quay, North Wall, Dublin 1",
      "Abbey Court Hostel - 29 Bachelors Walk, Dublin",
      "Maple Hotel Dublin - 75 Gardiner Street Lower, Dublin",
      "Abrahams Hostel - 82-83 Gardiner Street Lower, Dublin 1",
      "Maldron Hotel Parnell Square - Parnell Square West, Rotunda, Dublin 1",
      "The Trinity City Hotel - Pearse Street, Dublin 2",
      "The Spencer Hotel - Excise Walk, International Financial Services Centre, Dublin 1"
    ]
  },
  {
    "Mood": "Sad",
    "Location": "DFCsdc",
    "Timestamp": "2024-10-16T01:24:18.0619782+01:00",
    "Recommendations": [
      "No weather and recommendation data available."
    ]
  },
  {
    "Mood": "Happy",
    "Location": "Dublin",
    "Timestamp": "2024-10-16T01:25:41.06397+01:00",
    "Recommendations": [
      "The Morgan Hotel - 10-12 Fleet Street, Temple Bar, Dublin",
      "Temple Bar Inn - 40-47 Fleet Street, Temple Bar, Dublin 2",
      "The College Green Hotel Dublin, Autograph Collection - At, College Green, Dublin",
      "The Shelbourne, Autograph Collection - 27 Saint Stephen's Green, Dublin",
      "Hotel Riu Plaza The Gresham Dublin - 23 O'Connell Street Upper, Dublin",
      "Blooms Hotel - 3-6 Anglesea Street, Temple Bar, Dublin 2",
      "Trinity College Dublin - College Green, Dublin 2",
      "Anantara The Marker Dublin - Grand Canal Quay, Docklands, Dublin",
      "The Ferryman - 35 Sir John Rogerson's Quay, Grand Canal Dock, Dublin",
      "Maldron Hotel Smithfield - Smithfield Market, Smithfield, Dublin",
      "The Davenport Hotel - 8-10 Merrion Street Lower, Dublin",
      "Hilton Garden Inn Dublin City Centre - Custom House Quay, North Wall, Dublin 1",
      "Abbey Court Hostel - 29 Bachelors Walk, Dublin",
      "Maple Hotel Dublin - 75 Gardiner Street Lower, Dublin",
      "Abrahams Hostel - 82-83 Gardiner Street Lower, Dublin 1",
      "Maldron Hotel Parnell Square - Parnell Square West, Rotunda, Dublin 1",
      "The Trinity City Hotel - Pearse Street, Dublin 2",
      "The Spencer Hotel - Excise Walk, International Financial Services Centre, Dublin 1"
    ]
  },
  {
    "Mood": "Happy",
    "Location": "SVC\\SDC",
    "Timestamp": "2024-10-16T01:25:45.6265931+01:00",
    "Recommendations": [
      "No weather and recommendation data available. Try Again"
    ]
  }
]